gdoc_dumper/__init__.py
gdoc_dumper/downloader.py
gdoc_dumper/file_manager.py
gdoc_dumper/main.py
gdoc_dumper/py.typed
gdoc_dumper/enums/__init__.py
gdoc_dumper/enums/enums.py
gdoc_dumper/utils/__init__.py
gdoc_dumper/utils/logger.py
gdoc_dumper-0.2.2.dist-info/METADATA
gdoc_dumper-0.2.2.dist-info/WHEEL
gdoc_dumper-0.2.2.dist-info/licenses/LICENSE
gdoc_dumper-0.2.2.dist-info/RECORD
