Metadata-Version: 2.4
Name: gdoc-dumper
Version: 0.2.2
Summary: Lightweight python package for downloading Google Docs documents in various formats.
Author-email: natrofimov <nikolaytroofimov@gmail.com>
License-File: LICENSE
Requires-Python: >=3.12
Requires-Dist: aiofiles>=24.1.0
Requires-Dist: httpx>=0.28.1
Requires-Dist: twine>=6.1.0
